eztorchtils/__init__.py
eztorchtils/utils/__init__.py
eztorchtils/utils/arrays.py
eztorchtils/utils/logging.py
eztorchtils/utils/model_wrappers.py
eztorchtils/utils/structures.py
eztorchtils-0.3.6.dist-info/WHEEL
eztorchtils-0.3.6.dist-info/METADATA
eztorchtils-0.3.6.dist-info/LICENSE
eztorchtils-0.3.6.dist-info/RECORD
