Metadata-Version: 2.1
Name: eztorchtils
Version: 0.3.6
Summary: eds torch stuff
Home-page: https://github.com/ezhang7423/eztorchtils
License: MIT
Author: ezhang7423
Author-email: ezhang7423@student.palomar.edu
Requires-Python: >=3.8,<4.0
Classifier: Development Status :: 3 - Alpha
Classifier: Intended Audience :: Developers
Classifier: License :: OSI Approved :: MIT License
Classifier: Operating System :: OS Independent
Classifier: Programming Language :: Python :: 3
Classifier: Programming Language :: Python :: 3.8
Classifier: Programming Language :: Python :: 3.9
Classifier: Programming Language :: Python :: 3.10
Classifier: Programming Language :: Python :: 3.11
Classifier: Programming Language :: Python :: 3
Classifier: Programming Language :: Python :: 3.8
Classifier: Programming Language :: Python :: 3.9
Classifier: Topic :: Software Development :: Libraries :: Python Modules
Requires-Dist: einops (>=0.6.0,<0.7.0)
Requires-Dist: loguru (>=0.6.0,<0.7.0)
Requires-Dist: numpy (>=1.24.3,<2.0.0)
Requires-Dist: rich (>=13.3.3,<14.0.0)
Requires-Dist: tqdm (>=4.65.0,<5.0.0)
Project-URL: Repository, https://github.com/ezhang7423/eztorchtils
